django_templated_email-3.1.1.dist-info/licenses/AUTHORS
django_templated_email-3.1.1.dist-info/licenses/LICENSE
templated_email/__init__.py
templated_email/generic_views.py
templated_email/models.py
templated_email/urls.py
templated_email/utils.py
templated_email/views.py
templated_email/backends/__init__.py
templated_email/backends/vanilla_django.py
templated_email/migrations/0001_initial.py
templated_email/migrations/__init__.py
templated_email/templates/templated_email/saved_email.html
django_templated_email-3.1.1.dist-info/METADATA
django_templated_email-3.1.1.dist-info/WHEEL
django_templated_email-3.1.1.dist-info/top_level.txt
django_templated_email-3.1.1.dist-info/RECORD
